{
    "experiment_config": {
        "device": "cuda",
        "data_loading_option": "split_dataset_with_feature_prop",
        "model_type": "GAT",
        "dataset": "Pubmed",
        "num_clients": 10,
        "beta": 10000,
        "hop": 2
    },
    "rounds": [
        {
            "round": 1,
            "global_result": 0.499,
            "client_result": 0.4965652607126339
        },
        {
            "round": 2,
            "global_result": 0.5,
            "client_result": 0.5002574925226984
        },
        {
            "round": 3,
            "global_result": 0.508,
            "client_result": 0.5060491105360279
        },
        {
            "round": 4,
            "global_result": 0.519,
            "client_result": 0.5247459965723144
        },
        {
            "round": 5,
            "global_result": 0.502,
            "client_result": 0.4990225726491483
        }
    ],
    "summary": {
        "global_results": [
            0.499,
            0.5,
            0.508,
            0.519,
            0.502
        ],
        "client_results": [
            0.4965652607126339,
            0.5002574925226984,
            0.5060491105360279,
            0.5247459965723144,
            0.4990225726491483
        ],
        "average_global_result": 0.5056,
        "average_client_result": 0.5053280865985645,
        "std_global": 0.007391887445030538,
        "std_client": 0.010196397905365168
    }
}